s3_to_disk/__init__.py
s3_to_disk-0.1.2.dist-info/METADATA
s3_to_disk-0.1.2.dist-info/RECORD
s3_to_disk-0.1.2.dist-info/WHEEL
s3_to_disk-0.1.2.dist-info/entry_points.txt
s3_to_disk-0.1.2.dist-info/top_level.txt
