Metadata-Version: 2.1
Name: s3-to-disk
Version: 0.1.2
Summary: A simple tool to synchronizes S3 to a local folder
Home-page: https://github.com/kardaj/s3-to-disk
Author: Hassene Ben Salem
Author-email: bensalemhsn@gmail.com
License: UNKNOWN
Platform: UNKNOWN
Classifier: Programming Language :: Python :: 2
Classifier: Programming Language :: Python :: 3
Classifier: License :: OSI Approved :: MIT License
Classifier: Operating System :: OS Independent
Requires-Dist: future
Requires-Dist: boto3
Requires-Dist: awscli
